{"idr":"post:580342594@facebook/feed_self#580342594_10151256333042595","id":"3097caa6a237e60df602b74cde1b1d63_ba9ad0cd6","data":{"id":"580342594_10151256333042595","from":{"name":"Jeremie Miller","id":"580342594"},"story":"Jeremie Miller likes a status.","story_tags":{"0":[{"id":"580342594","name":"Jeremie Miller","offset":0,"length":14,"type":"user"}]},"privacy":{"value":""},"type":"status","created_time":1361177467,"updated_time":1361177467,"comments":{"count":0}},"at":1361177467000,"types":{"status":true,"text":true},"oembed":{"type":"text","text":"Jeremie Miller likes a status.","source_name":"facebook"}}